{"organizations": [], "uuid": "e044ab89b786e27622700047216dbf4f29c8f461", "thread": {"social": {"gplus": {"shares": 0}, "pinterest": {"shares": 0}, "vk": {"shares": 0}, "linkedin": {"shares": 0}, "facebook": {"likes": 0, "shares": 0, "comments": 0}, "stumbledupon": {"shares": 0}}, "site_full": "www.foxnews.com", "main_image": "http://a57.foxnews.com/media2.foxnews.com/BrightCove/694940094001/2016/08/31/0/0/694940094001_5106884367001_2553565088001-vs.jpg?ve=1", "site_section": "http://www.foxnews.com/about/rss/feedburner/foxnews/politics", "section_title": "FOX News", "url": "http://www.foxnews.com/politics/2016/10/01/trump-us-has-right-to-choose-immigrants-most-likely-to-flourish.html", "country": "EU", "domain_rank": 185, "title": "Trump: US has right to choose immigrants most likely to flourish", "performance_score": 0, "site": "foxnews.com", "participants_count": 15, "title_full": "Trump: US has right to choose immigrants most likely to flourish | Fox News", "spam_score": 0.0, "site_type": "news", "published": "2016-10-01T03:00:00.000+03:00", "replies_count": 16, "uuid": "7dbbc5a195f53c7a02b63f9ea7c1d993e6815d71"}, "author": "ioutbidu", "url": "http://www.foxnews.com/politics/2016/10/01/trump-us-has-right-to-choose-immigrants-most-likely-to-flourish.html#post-4", "ord_in_thread": 4, "title": "", "locations": [], "entities": {"persons": [], "locations": [], "organizations": []}, "highlightText": "", "language": "english", "persons": [], "text": "Being an American in any vernacular means \n\\being a citizen of The United States of America...\nNot an illegal alien, migrant worker, undocumented flavor of the month...", "external_links": [], "published": "2016-09-01T10:02:00.000+03:00", "crawled": "2016-09-01T05:11:04.736+03:00", "highlightTitle": ""}