{"organizations": [], "uuid": "70b9483dc512c2bf26bb4fada12b60c99687eeb5", "thread": {"social": {"gplus": {"shares": 0}, "pinterest": {"shares": 0}, "vk": {"shares": 0}, "linkedin": {"shares": 0}, "facebook": {"likes": 0, "shares": 0, "comments": 0}, "stumbledupon": {"shares": 0}}, "site_full": "insider.foxnews.com", "main_image": "http://insider.foxnews.com/sites/insider.foxnews.com/files/styles/780/public/090716_jet.jpg?itok=PW4FDQ8D", "site_section": "", "section_title": "", "url": "http://insider.foxnews.com/2016/09/07/russian-jet-flies-within-10-feet-us-spy-plane-defense-officials-say", "country": "US", "domain_rank": 185, "title": "Russian Jet Flies Within 10 Feet of U.S. Spy Plane, Officials Say | Fox News Insider", "performance_score": 0, "site": "foxnews.com", "participants_count": 0, "title_full": "Russian Jet Flies Within 10 Feet of U.S. Spy Plane, Officials Say | Fox News Insider", "spam_score": 0.083, "site_type": "news", "published": "2016-09-08T02:17:00.000+03:00", "replies_count": 0, "uuid": "70b9483dc512c2bf26bb4fada12b60c99687eeb5"}, "author": "Fox News Insider", "url": "http://insider.foxnews.com/2016/09/07/russian-jet-flies-within-10-feet-us-spy-plane-defense-officials-say", "ord_in_thread": 0, "title": "Russian Jet Flies Within 10 Feet of U.S. Spy Plane, Officials Say | Fox News Insider", "locations": [], "entities": {"persons": [{"name": "neil", "sentiment": "negative"}, {"name": "hillary clinton", "sentiment": "none"}, {"name": "marc thiessen", "sentiment": "none"}, {"name": "oliver north", "sentiment": "none"}, {"name": "brit hume", "sentiment": "none"}, {"name": "trump", "sentiment": "none"}, {"name": "donald trump", "sentiment": "none"}, {"name": "watters", "sentiment": "none"}, {"name": "ben carson", "sentiment": "none"}, {"name": "mike flynn", "sentiment": "none"}, {"name": "hannity", "sentiment": "none"}, {"name": "sebastian gorka", "sentiment": "none"}, {"name": "bill o'reilly", "sentiment": "none"}, {"name": "newt gingrich", "sentiment": "none"}], "locations": [{"name": "philadelphia", "sentiment": "none"}, {"name": "chicago", "sentiment": "none"}], "organizations": [{"name": "u.s. spy plane", "sentiment": "negative"}, {"name": "big gamble", "sentiment": "none"}, {"name": "black lives matter", "sentiment": "none"}]}, "highlightText": "", "language": "english", "persons": [], "text": "4 P \nNeil’s BACK - and taking on 2016! From the economy to national security, get expert insight on a must-see Your World . 7 P \nShowdown in the South! Hillary Clinton and Donald Trump square off, and the gloves come off. Newt Gingrich goes On The Record with Brit Hume . 8 \nWhy aren't politicians talking about blacks killing blacks in Chicago? The O'Reilly Factor investigates. 9 P \nWho’s ready to be our next commander-in-chief? The Kelly File gets live reaction to the IAVA Commander in Chief Forum, with insight from Marc Thiessen and Dr. Ben Carson . Then at 10:00 , Lt. Gen. Mike Flynn , Lt. Col. Oliver North , and Dr. Sebastian Gorka weigh in on Hannity . The O'Reilly Factor Is 'Black Lives Matter' a Racist Term? Watters' World Tackles Racism Sep 06, 2016 9:14pm One of the biggest issues of this presidential race is race itself. Watters traveled to Philadelphia and asked people about the definition of racism, whether Black Lives Matter is a racist group, and... Sep 06, 2016 8:51pm Donald Trump told The O'Reilly Factor that he's not feeling any pressure to release his tax returns. O'Reilly Talks About Trump's 'Big Gamble' Sep 06, 2016 8:15pm In tonight's talking points, Bill O'Reilly weighed in on Donald Trump's \"big gamble\" - and that is banking his campaign on American voters being fed up with a lack of immigration enforcement. ", "external_links": [], "published": "2016-09-08T02:17:00.000+03:00", "crawled": "2016-09-07T21:19:56.192+03:00", "highlightTitle": ""}